hazard_feed/__init__.py
hazard_feed/admin.py
hazard_feed/apps.py
hazard_feed/config.py
hazard_feed/consumers.py
hazard_feed/forms.py
hazard_feed/jobs.py
hazard_feed/models.py
hazard_feed/routing.py
hazard_feed/serializers.py
hazard_feed/signals.py
hazard_feed/tests.py
hazard_feed/urls.py
hazard_feed/utils.py
hazard_feed/fixtures/email_templates.json
hazard_feed/fixtures/feeds.json
hazard_feed/fixtures/hazard_levels.json
hazard_feed/fixtures/rss_urls.json
hazard_feed/management/__init__.py
hazard_feed/management/commands/__init__.py
hazard_feed/management/commands/add_hazard_levels_to_weather_recipients.py
hazard_feed/management/commands/date_define.py
hazard_feed/management/commands/schedule_jobs.py
hazard_feed/migrations/0001_initial.py
hazard_feed/migrations/0002_hazardlevels_color_code.py
hazard_feed/migrations/0003_weatherrecipients.py
hazard_feed/migrations/0004_hazardfeeds_is_sent.py
hazard_feed/migrations/0005_auto_20200204_2313.py
hazard_feed/migrations/0006_weatherrecipients_uuid.py
hazard_feed/migrations/0007_emailtemplates.py
hazard_feed/migrations/0008_initial_hazard_levels_import.py
hazard_feed/migrations/0009_initial_email_templates_import.py
hazard_feed/migrations/0010_rssfeedurl.py
hazard_feed/migrations/0011_rss_feed_url_initial.py
hazard_feed/migrations/0012_auto_20200322_1820.py
hazard_feed/migrations/0013_emailactivationcode_is_activate.py
hazard_feed/migrations/0014_remove_emailactivationcode_session.py
hazard_feed/migrations/0015_auto_20200929_1859.py
hazard_feed/migrations/0016_auto_20201001_2227.py
hazard_feed/migrations/0017_weatherrecipients_hazard_levels.py
hazard_feed/migrations/0018_auto_20201104_0806.py
hazard_feed/migrations/0019_weatherrecipientseditcandidate.py
hazard_feed/migrations/__init__.py
hazard_feed/static/hazard_feed/static/js/tinymce/tinymce.min.js
hazard_feed/templates/hazard_feed/code_email.html
hazard_feed/templates/hazard_feed/weather_mail.html
hazard_feed/templates/hazard_feed/ws.html
hazard_feed/views/__init__.py
hazard_feed-0.2.5.dist-info/LICENSE
hazard_feed-0.2.5.dist-info/METADATA
hazard_feed-0.2.5.dist-info/WHEEL
hazard_feed-0.2.5.dist-info/top_level.txt
hazard_feed-0.2.5.dist-info/RECORD
